ensbinclass/__init__.py
ensbinclass/__main__.py
ensbinclass/classifier.py
ensbinclass/ensemble.py
ensbinclass/featureSelection.py
ensbinclass/gprofiler.py
ensbinclass/modelEvaluation.py
ensbinclass/performanceMetrics.py
ensbinclass/preprocessing.py
tests/test_classifier.py
tests/test_ensemble.py
tests/test_featureSelection.py
tests/test_modelEvaluation.py
tests/test_preprocessing.py
ensemble_binclass-1.0.12.dist-info/METADATA
ensemble_binclass-1.0.12.dist-info/WHEEL
ensemble_binclass-1.0.12.dist-info/top_level.txt
ensemble_binclass-1.0.12.dist-info/RECORD
