Metadata-Version: 2.4
Name: ensemble-binclass
Version: 1.0.12
Summary: Feature selection and ensemble classification
Home-page: https://github.com/biocsuwb/ensemble-binclass
Author: Szymon Kolodziejski
Author-email: Szymon Kołodziejski <koodziejskisz@outlook.com>
Project-URL: source, https://github.com/biocsuwb/ensemble-binclass
Keywords: feature selection,ensemble classification,machine learning,omnic data
Classifier: License :: OSI Approved :: MIT License
Classifier: Programming Language :: Python
Classifier: Programming Language :: Python :: 3
Requires-Python: >=3.9
Requires-Dist: pandas~=2.2.0
Requires-Dist: scikit-learn~=1.5.0
Requires-Dist: xgboost~=2.0.0
Requires-Dist: numpy~=2.2.0
Requires-Dist: ReliefF~=0.1.2
Requires-Dist: scipy~=1.15.0
Requires-Dist: mrmr-selection~=0.2.8
Requires-Dist: matplotlib~=3.10.0
Requires-Dist: pytest~=8.3.0
Requires-Dist: pytest-cov~=6.0.0
Requires-Dist: seaborn~=0.13.0
Requires-Dist: gprofiler-official~=0.3.5
Requires-Dist: pypandoc~=1.15.0
Dynamic: author
Dynamic: home-page
Dynamic: requires-python
